tvi/solphit/discera/capability/__init__.py
tvi/solphit/discera/capability/weather.py
tvi_solphit_discera_capability_weather-0.1.2.dist-info/licenses/LICENSE
tvi_solphit_discera_capability_weather-0.1.2.dist-info/METADATA
tvi_solphit_discera_capability_weather-0.1.2.dist-info/WHEEL
tvi_solphit_discera_capability_weather-0.1.2.dist-info/entry_points.txt
tvi_solphit_discera_capability_weather-0.1.2.dist-info/top_level.txt
tvi_solphit_discera_capability_weather-0.1.2.dist-info/RECORD
