Metadata-Version: 2.4
Name: tvi-solphit-discera-capability-weather
Version: 0.1.2
Summary: Whats the weather like in.... and when....
Author: Tobias Hagenbeek
License: MIT License
Project-URL: Homepage, https://github.com/SolphIT/tvi-solphit-discera-capability-weather
Project-URL: Changelog, https://github.com/SolphIT/tvi-solphit-discera-capability-weather/blob/main/CHANGELOG.md
Keywords: discera,plugin,capability,weather
Classifier: Programming Language :: Python :: 3
Classifier: Programming Language :: Python :: 3.12
Classifier: License :: OSI Approved :: MIT License
Classifier: Operating System :: OS Independent
Requires-Python: >=3.9
License-File: LICENSE
Requires-Dist: tvi-solphit-base>=0.2.0
Provides-Extra: test
Requires-Dist: pytest>=7.0; extra == "test"
Dynamic: license-file
